.gitignore
.gitlab-ci.yml
.mailmap
CHANGELOG.md
CMakeLists.txt
CONTRIBUTING.md
COPYING
INSTALL
LICENSE.md
README.md
config.h.cmake
dune-common.pc.in
dune.module
pyproject.toml
setup.py
.codechecker/config.json
.codechecker/config.json.license
.codechecker/skipfile
.codechecker/skipfile.license
.reuse/dep5
LICENSES/BSD-3-Clause.txt
LICENSES/FSFAP.txt
LICENSES/LicenseRef-GPL-2.0-only-with-DUNE-exception.txt
bin/CMakeLists.txt
bin/dune-add-spdx
bin/dune-ctest
bin/dune-git-whitespace-hook
bin/dunecontrol
bin/dunepackaging.py
bin/duneproject
bin/find_modules.py
bin/rebuild-dune-pypi.sh
cmake/CMakeLists.txt
cmake/modules/AddBLASLapackFlags.cmake
cmake/modules/AddGMPFlags.cmake
cmake/modules/AddMETISFlags.cmake
cmake/modules/AddMPIFlags.cmake
cmake/modules/AddPTScotchFlags.cmake
cmake/modules/AddParMETISFlags.cmake
cmake/modules/AddQuadMathFlags.cmake
cmake/modules/AddSuiteSparseFlags.cmake
cmake/modules/AddTBBFlags.cmake
cmake/modules/AddThreadsFlags.cmake
cmake/modules/AddVcFlags.cmake
cmake/modules/CMakeBuiltinFunctionsDocumentation.cmake
cmake/modules/CMakeLists.txt
cmake/modules/CheckCXXFeatures.cmake
cmake/modules/DuneAddLibrary.cmake
cmake/modules/DuneAddPybind11Module.cmake
cmake/modules/DuneCommonMacros.cmake
cmake/modules/DuneDefaultIncludeDirectories.cmake
cmake/modules/DuneDoc.cmake
cmake/modules/DuneDoxygen.cmake
cmake/modules/DuneEnableAllPackages.cmake
cmake/modules/DuneExecuteProcess.cmake
cmake/modules/DuneInstance.cmake
cmake/modules/DuneMacros.cmake
cmake/modules/DuneModuleDependencies.cmake
cmake/modules/DuneModuleInformation.cmake
cmake/modules/DunePathHelper.cmake
cmake/modules/DunePkgConfig.cmake
cmake/modules/DunePolicy.cmake
cmake/modules/DuneProject.cmake
cmake/modules/DunePythonCommonMacros.cmake
cmake/modules/DunePythonCompiler.cmake
cmake/modules/DunePythonFindPackage.cmake
cmake/modules/DunePythonInstallPackage.cmake
cmake/modules/DunePythonTestCommand.cmake
cmake/modules/DunePythonVirtualenv.cmake
cmake/modules/DuneReplaceProperties.cmake
python/dune_common.egg-info/PKG-INFO
python/dune_common.egg-info/SOURCES.txt
python/dune_common.egg-info/dependency_links.txt
python/dune_common.egg-info/requires.txt
python/dune_common.egg-info/top_level.txt
